CHANGES.txt
bootstrap.py
buildout.cfg
setup.py
src/zc/__init__.py
src/zc.ssl.egg-info/PKG-INFO
src/zc.ssl.egg-info/SOURCES.txt
src/zc.ssl.egg-info/dependency_links.txt
src/zc.ssl.egg-info/namespace_packages.txt
src/zc.ssl.egg-info/not-zip-safe
src/zc.ssl.egg-info/requires.txt
src/zc.ssl.egg-info/top_level.txt
src/zc/ssl/__init__.py
src/zc/ssl/certs.pem
src/zc/ssl/tests.py
src/zc/ssl/tests.txt