Metadata-Version: 1.0
Name: zc.ssl
Version: 1.2
Summary: An HTTPSConnection implementation with the new ssl module
Home-page: UNKNOWN
Author: Zope Corporation
Author-email: zope-dev@zope.org
License: ZPL 2.1
Keywords: ssl https
Platform: UNKNOWN
